dart_trec_commons/__init__.py
dart_trec_commons/exceptions.py
dart_trec_commons/shared_counter.py
dart_trec_commons/singleton.py
dart_trec_commons/commons/__init__.py
dart_trec_commons/commons/utils.py
dart_trec_commons/dao/__init__.py
dart_trec_commons/dao/bucket_dao.py
dart_trec_commons/dao/bucket_dao_impl.py
dart_trec_commons/dao/db_connection.py
dart_trec_commons/dao/issue_dao.py
dart_trec_commons/dao/issue_dao_impl.py
dart_trec_commons/factories/__init__.py
dart_trec_commons/factories/simple_factory.py
dart_trec_commons/indexers/__init__.py
dart_trec_commons/ml/__init__.py
dart_trec_commons/ml/mlmodel.py
dart_trec_commons/ml/mlmodel_store.py
dart_trec_commons/ml/classifiers/__init__.py
dart_trec_commons/ml/encoders/__init__.py
dart_trec_commons/ml/evaluation/__init__.py
dart_trec_commons/ml/recommenders/__init__.py
dart_trec_commons/ml/searchers/__init__.py
dart_trec_commons/model_manager/__init__.py
dart_trec_commons/model_manager/abstract_model_manager.py
dart_trec_commons/model_manager/active_model_manager.py
dart_trec_commons/model_manager/downloader.py
dart_trec_commons/model_manager/model_manager.py
dart_trec_commons/model_manager/simple_model_manager.py
dart_trec_commons/model_manager/uploader.py
dart_trec_commons/split_dataset/__init__.py
dart_trec_commons/split_dataset/splitter.py
dart_trec_commons/split_dataset/splitters/__init__.py
dart_trec_commons/split_dataset/splitters/learner_prod_splitter.py
dart_trec_commons/split_dataset/splitters/scikit_splitter.py
dart_trec_commons/split_dataset/splitters/split.py
dart_trec_commons/utils/__init__.py
dart_trec_commons/utils/envutils.py
dart_trec_commons-2.8.3.dist-info/LICENSE
dart_trec_commons-2.8.3.dist-info/METADATA
dart_trec_commons-2.8.3.dist-info/WHEEL
dart_trec_commons-2.8.3.dist-info/dependency_links.txt
dart_trec_commons-2.8.3.dist-info/top_level.txt
dart_trec_commons-2.8.3.dist-info/RECORD
