Metadata-Version: 2.1
Name: dart-trec-commons
Version: 2.8.3
Summary: T-REC Commons libs
Home-page: https://github.sec.samsung.net/SOL/dart-trec-commons
Author: SIDIA
Author-email: sidia@sidia.com
License: UNKNOWN
Platform: UNKNOWN
Classifier: Programming Language :: Python :: 3
Classifier: License :: OSI Approved :: Apache Software License
Classifier: Operating System :: OS Independent
Requires-Python: ~=3.7
License-File: LICENSE
Requires-Dist: importlib-metadata (==4.13.0)
Requires-Dist: minio (==6.0.2)
Requires-Dist: numpy (<2,>=1.22.0)
Requires-Dist: pandas (==1.5.3)
Requires-Dist: pymongo (==4.6.3)
Requires-Dist: scikit-learn (>=1.2.2)
